ngobot_json/__init__.py
ngobot_json/pyresponse.py
ngobot_json-1.1.9.dist-info/LICENSE
ngobot_json-1.1.9.dist-info/METADATA
ngobot_json-1.1.9.dist-info/WHEEL
ngobot_json-1.1.9.dist-info/top_level.txt
ngobot_json-1.1.9.dist-info/RECORD
