Metadata-Version: 2.1
Name: ngobot-json
Version: 1.1.9
Summary: A Python JSON Format
Home-page: https://github.com/ngobot/ngobot_json
Author: Nseobong Gregory obot
Author-email: obot.greg@icloud.com
License: UNKNOWN
Project-URL: Bug Tracker, https://github.com/ngobot/ngobot_json/issues
Platform: UNKNOWN
Classifier: Programming Language :: Python :: 3
Classifier: License :: OSI Approved :: MIT License
Classifier: Operating System :: OS Independent
Requires-Python: >=3.6
License-File: LICENSE
